honey/__init__.py
honey/asyncio.py
honey/dateutil.py
honey/opencv.py
honey/retry.py
honey/utils.py
honey/tests/__init__.py
honey/tests/test_asyncio.py
honey/tests/test_dateutil.py
honey/tests/test_opencv.py
honey/tests/test_retry.py
honey/tests/test_utils.py
bepro_python_honey-0.0.1.8.dist-info/METADATA
bepro_python_honey-0.0.1.8.dist-info/WHEEL
bepro_python_honey-0.0.1.8.dist-info/top_level.txt
bepro_python_honey-0.0.1.8.dist-info/RECORD
