Metadata-Version: 2.1
Name: bepro-python-honey
Version: 0.0.1.8
Summary: A utility package for Bepro Company
Home-page: https://github.com/bepro-company/bepro-python-honey
Author: Bepro Company
Author-email: dev@bepro11.com
License: UNKNOWN
Platform: UNKNOWN
Classifier: Programming Language :: Python :: 3.6
Classifier: Programming Language :: Python :: 3.7
Classifier: Programming Language :: Python :: 3.8
Classifier: Programming Language :: Python :: 3.9
